examples/color.py
examples/basic_video_out.py
examples/__init__.py
examples/basic_chat.py
python_twitch_stream-1.0.2.dist-info/metadata.json
python_twitch_stream-1.0.2.dist-info/top_level.txt
python_twitch_stream-1.0.2.dist-info/METADATA
python_twitch_stream-1.0.2.dist-info/DESCRIPTION.rst
python_twitch_stream-1.0.2.dist-info/RECORD
python_twitch_stream-1.0.2.dist-info/WHEEL
twitchstream/outputvideo.py
twitchstream/chat.py
twitchstream/__init__.py
