Metadata-Version: 2.0
Name: python-twitch-stream
Version: 1.0.2
Summary: An interface to the Twitch website, to interact with their video and chat
Home-page: https://github.com/317070/python-twitch-stream
Author: Jonas Degrave
Author-email: erstaateenknolraapinmijntuin+pythontwitch@gmail.com
License: MIT
Keywords: twitch,stream,video,chat
Platform: UNKNOWN
Classifier: Development Status :: 5 - Production/Stable
Classifier: Intended Audience :: Developers
Classifier: Intended Audience :: Science/Research
Classifier: Intended Audience :: Other Audience
Classifier: License :: OSI Approved :: MIT License
Classifier: Natural Language :: English
Classifier: Operating System :: POSIX :: Linux
Classifier: Programming Language :: Python :: 2.7
Classifier: Programming Language :: Python :: 3.4
Classifier: Topic :: Communications :: Chat :: Internet Relay Chat
Classifier: Topic :: Multimedia :: Video
Requires-Dist: numpy
Provides-Extra: testing
Requires-Dist: mock; extra == 'testing'
Requires-Dist: pytest; extra == 'testing'
Requires-Dist: pytest-cov; extra == 'testing'
Requires-Dist: pytest-pep8; extra == 'testing'
